DESCRIPTION.rst
MANIFEST.in
README.rst
setup.py
restart_docker/__init__.py
restart_docker.egg-info/PKG-INFO
restart_docker.egg-info/SOURCES.txt
restart_docker.egg-info/dependency_links.txt
restart_docker.egg-info/entry_points.txt
restart_docker.egg-info/requires.txt
restart_docker.egg-info/top_level.txt