Metadata-Version: 1.1
Name: restart-docker
Version: 0.0.1
Summary: A tool for restarting docker containers if their configuration or base image changes.
Home-page: https://github.com/albertkoch/restart_docker
Author: Albert Koch
Author-email: kocha@slagit.net
License: GPLv3
Platform: UNKNOWN
Classifier: Development Status :: 3 - Alpha
Classifier: Environment :: Console
Classifier: Intended Audience :: System Administrators
Classifier: License :: OSI Approved :: GNU General Public License v3 (GPLv3)
Classifier: Programming Language :: Python :: 3.4
